{"gs_ids": ["APP.5.3.A9", "APP.5.3.A10"], "coverage": "teilweise", "confidence": 0.72, "rationale": "Die GS++-Anforderung KONF.13.2.2 fordert die automatische Verifikation der Serversignatur eingehender E-Mails (Authentizität), insbesondere anhand DKIM (Unterscheidung zu PGP, Umgang mit fehlendem DKIM) sowie kryptographische Verfahren gemäß IDM. Das wird durch APP.5.3.A9 weitgehend adressiert: Dort wird explizit verlangt, eingehende E-Mails auf SPF und DKIM zu überprüfen, und DKIM/SPF als Authentisierungsmechanismen zu nutzen; außerdem werden Maßnahmen/Umgang bei Bedarf über DMARC beschrieben (z.B. Abweisung im Fehlerfall) und weitere Absicherungen (z.B. DANE/MTA-STS) genannt. APP.5.3.A10 ergänzt die generelle Pflicht, für E-Mails Ende-zu-Ende-Verschlüsselung und digitale Signaturen einzusetzen und nur aktuelle kryptographische Verfahren zu verwenden.", "gap_notes": "Nicht vollständig abgedeckt: (1) Der GS++-Text betont explizit die automatische Authentifizierung der Serversignatur eingehender E-Mails und den konkreten Vergleich/Abgrenzung zu PGP (GS-Kandidaten nennen zwar DKIM vs. PGP nicht explizit). (2) Der GS++-Hinweis, dass E-Mails ohne DKIM unzureichend authentifiziert sind und daher gezielt gegen Spoofing/Phishing durch Kompromissmaßnahmen (Warnhinweis, Allowlisting, Greylisting, Quarantäne, Anomalieerkennung) behandelt werden sollen, ist in APP.5.3.A9 nur indirekt über DMARC-Abweisung/Reporte und ohne die genannten Kompromissmaßnahmen abgebildet. (3) Die Formulierung „im Einklang mit den Festlegungen des Identitäts- und Berechtigungsmanagements (IDM)“ wird von den Kandidaten nicht mit gleicher Bedeutung/Bezug explizit adressiert."}