{"gs_ids": ["OPS.1.1.7.A8", "OPS.1.1.7.A11", "OPS.1.1.7.A24", "SYS.3.2.2.A20", "APP.4.4.A13", "OPS.1.1.7.A14"], "coverage": "teilweise", "confidence": 0.63, "rationale": "Die GS++-Anforderung KONF.2.5.1 („Automatische Konfigurationsverwaltung“ inkl. Aktivierung einer Konfigurationsüberprüfung, Einheitlichkeit/Sollzustand sowie Abweichungsbehandlung) wird durch mehrere Kandidatenbausteine teilweise abgedeckt: OPS.1.1.7.A8 fordert eine zentrale Konfigurationsverwaltung inkl. automatischer Netzverteilung und Installation/Aktivierung, was dem Gedanken „automatisch konfigurieren“ entspricht. OPS.1.1.7.A11 beschreibt den regelmäßigen Soll-Ist-Vergleich der verwalteten Konfiguration/Skripte gegen den Sollzustand, was das in KONF.2.5.1 genannte „Überprüfung der Konfiguration“ adressiert. OPS.1.1.7.A24 ergänzt die regelmäßige automatisierte Überprüfung sicherheitsrelevanter Konfigurationen auf Abweichungen/Sollzustand mittels Detektionssystemen. SYS.3.2.2.A20 konkretisiert für MDM die regelmäßige Überprüfung von Sicherheitseinstellungen und das Korrigieren von Abweichungen, ebenfalls passend zu „bei Abweichungen“ und zur Wirksamkeit von Konfigurationen. APP.4.4.A13 deckt ein automatisches Audit von Konfigurationen gegen eine erlaubte Liste/Benchmarks ab (starker Bezug auf automatisierte Konfigurationsüberprüfung, wenn auch im Kubernetes-Kontext). OPS.1.1.7.A14 adressiert das Vorhandensein einer zentralen Konfigurationsverwaltung mit versionierung/änderungsverfolgung, was zu „einheitliche Konfiguration“ beiträgt. Nicht alle Aspekte (insb. explizite Aktivierung der Konfigurationsüberprüfung über ein spezifisches Statement/Parameter, sowie die im Text genannten konkreten Umsetzungsarten wie UEM/MDM/Intune/Ansible und die Alternativen „automatischer Mechanismus vs. manuelle Entscheidung“) sind in dieser Kandidatenauswahl vollständig abgedeckt.", "gap_notes": "Fehlende/ungenügend abgedeckte Aspekte: (1) explizites Setzen/„KANN ... aktivieren“ einer Konfigurationsüberprüfung über einen Parameter (in den Kandidaten eher generisch SOLLTEN/MÜSSEN, nicht als Aktivierungsoption formuliert), (2) konkrete beispielhafte Umsetzungstechnologien (UEM/MDM, Intune, Ansible) sind nur indirekt bzw. teilweise (MDM erwähnt, Intune/Ansible nicht genannt), (3) klare Regel, dass bei Abweichungen entweder automatisiert nachkonfiguriert ODER manuell entschieden wird (in den Kandidaten häufig „korrigieren/verteilen/erzwingen“, aber nicht die explizite Entscheidungsalternative „automatisiert oder manuell“)."}