{"coverage": "teilweise", "confidence": 0.75, "gs_ids": ["DER.2.2.A13", "DER.2.2.A3"], "gap_notes": "REA.2.5.3 requires a specific SLA guarantee for first response timeframes within the contract with a forensics service provider. While DER.2.2.A13 addresses framework contracts with forensics service providers and DER.2.2.A3 covers pre-selection documentation, neither explicitly mandates the service level agreement for guaranteed first response timeframe within a specific deadline as required by REA.2.5.3 guidance.", "rationale": "DER.2.2.A13 (Hoch) explicitly requires framework contracts with forensics service providers for faster forensic investigation of incidents, and DER.2.2.A3 (Basis) requires identification and documentation of suitable forensics service providers in the preparation phase. Both candidates address the contract preparation and provider qualification aspects of REA.2.5.3. However, REA.2.5.3 has a specific requirement for guaranteeing first response within a specific timeframe, which is not explicitly covered in the Grundschutz candidates. The candidates cover contract/preparation aspects but miss the SLA service level commitment."}