{"gs_ids": ["CON.3.A14", "SYS.1.1.A34", "SYS.2.1.A38", "SYS.1.8.A20", "CON.7.A10"], "coverage": "teilweise", "confidence": 0.74, "rationale": "Die GS++-Anforderung NOT.4.8 „Verschlüsselte Datensicherung“ wird durch mehrere Kandidaten teilweise abgedeckt: (1) CON.3.A14 adressiert den Schutz von Datensicherungen vor unbefugtem Zugriff (u. a. Schutz vor Überschreiben). (2) SYS.1.1.A34 adressiert Verschlüsselung von Datenträgern (Festplatten-/Full Disk/Volume Encryption) und damit einen zentralen technischen Aspekt von „verschlüsselte Datensicherung“. (3) SYS.2.1.A38 ergänzt die Notfallplanung im Zusammenhang mit Wiederanlaufmaßnahmen und sicher hinterlegten Passwörtern/kryptografischen Schlüsseln (Key Management als wesentlicher Punkt aus der GS++-Guidance). (4) SYS.1.8.A20 behandelt Notfallpläne für Speicherlösungen, inklusive regelmäßiger Übungen und Post-Notfall-Datenlöschung (funktionaler Notfall-/Betriebskontext rund um Datensicherungen, jedoch ohne explizite Verschlüsselungsforderung für Backups). (5) CON.7.A10 ergänzt weitere Aspekte der Verschlüsselung in Zusammenhang mit kryptografischen Schlüsseln (getrennte Aufbewahrung), was den Key-Management-Aspekt aus der GS++-Anforderung unterstützt. Insgesamt fehlt jedoch die explizite, direkte Kopplung „Notfallplanung soll die Datensicherung durch … verschlüsseln“ sowie die konkrete Ausgestaltung der Verschlüsselung speziell für Sicherungsarchive/Backup-Stores (Disk Encryption vs. dateibasierte Verschlüsselung von Sicherungs-Archives) und der Hinweis auf anerkannte Algorithmen (BSI TR-02102).", "gap_notes": "Nicht vollständig abgedeckt: (a) explizite Pflicht in der Notfallplanung, die Datensicherung zu verschlüsseln (stattdessen eher genereller Schutz/verschlüsselung von Datenträgern), (b) konkrete Unterscheidung/Optionen wie „Disk Encryption am Sicherungsspeicher“ vs. „dateibasierte Verschlüsselung jedes einzelnen Sicherungs-Archives“, (c) explizite Bezugnahme auf anerkannte Algorithmen (BSI TR-02102), (d) Sicherstellung, dass im Ernstfall der Zugriff auf die Datensicherung wegen fehlender Zugangsdaten nicht unmöglich wird (Key Management/Prozess sicherer Wiederherstellung) wird nur indirekt über „sichere Hinterlegung“ abgedeckt."}