{"gs_ids": ["SYS.2.1.A13", "IND.2.1.A1", "SYS.1.7.A6", "SYS.2.1.A36", "OPS.1.1.7.A6"], "coverage": "teilweise", "confidence": 0.62, "rationale": "Die GS++-Anforderung KONF.5.1.1 verlangt, dass der Zugriff auf die Firmware (UEFI/Embedded) gemäß Identitäts- und Berechtigungsmanagement authentifiziert wird, um unautorisierte Firmware-Änderungen (z. B. Sicherheitsfunktionen/TPM) zu verhindern und dabei auch aktuelle kryptographische Verfahren einzusetzen (entsprechend BER). SYS.2.1.A13 deckt den Schutz von Firmware/UEFI-Bereichen vor unberechtigten Veränderungen mit Passwort/administrativen Berechtigungen ab. IND.2.1.A1 adressiert den kontrollierten Zugriff auf (Konfigurations-)Schnittstellen und das Ändern von Konfigurationen nur nach Authentisierung/Freigabe. SYS.1.7.A6 ergänzt spezifisch organisatorisch/technisch abgesicherte Wartungs-/Fernwartungszugriffe auf Firmware-Änderungen (autorisierte Personen, explizite Freigabe, gesicherte Verbindungen). SYS.2.1.A36 behandelt zwar primär SecureBoot/TPM-Absicherung durch Signierung/Schlüsselmaterial, passt aber als Referenz zum Thema TPM-Funktionalität und Schutzwirkung bei UEFI-Firmware-Komponenten. OPS.1.1.7.A6 liefert eine generische Anforderung an Authentisierungsmethoden und die regelmäßige Überprüfung der kryptografischen Verfahren/Schlüssel sowie Autorisierung, was die Formulierung „im Einklang mit den … Anforderungen zum Identitäts- und Berechtigungsmanagement“ und die Kryptographie-Anforderung teilweise stützt. Insgesamt fehlen jedoch eindeutige, direkte Aussagen, dass die Firmware-Zugangs-Authentifizierung explizit nach dem Identitäts- und Berechtigungsmanagement (BER) erfolgt und dass die beschriebenen kryptographischen Verfahren konkret für die Firmware-Authentifizierung anzuwenden sind.", "gap_notes": "Nicht vollständig abgedeckt: (1) Die klare Vorgabe, dass die Authentifizierung für den Firmwarezugriff explizit „im Einklang mit den … Anforderungen zum Identitäts- und Berechtigungsmanagement“ (BER) erfolgt. (2) Die GS-Kandidaten nennen meist Passwort/Autorisierung, aber nicht in der geforderten Tiefe die Verwendung aktueller kryptographischer Verfahren speziell für den Firmware-Zugriff (KONF: Authentifizierung + Kryptographie-Verfahren). (3) KONF nennt als Relevanzbezug insbesondere Einstellungen von Sicherheitsfunktionen/Netzanbindung; die Kandidaten adressieren zwar Firmware-Schutz bzw. Wartungszugriff, aber nicht durchgängig genau diese Schwerpunktbereiche für die Authentifizierung."}