{"gs_ids": ["OPS.2.3.A10", "OPS.3.2.A18", "OPS.2.3.A24", "OPS.3.2.A3", "OPS.3.2.A19"], "coverage": "teilweise", "confidence": 0.66, "rationale": "Die GS++-Anforderung BES.5.6.2 zielt auf die Autorisierung von Unterauftragnehmern durch den Auftraggeber (vorherige Zustimmung, um unkontrollierte/ungeprüfte Dritte und Risiken bzgl. Qualifikation/Vertrauenswürdigkeit sowie Zugriff auf vertrauliche/kritische Prozesse zu verhindern). Teilaspekte davon werden durch OPS.2.3.A10 adressiert, indem für Outsourcing-Vorhaben eine zuständige, befugte Schnittstellenperson und Einbindung in Vertragsgestaltung vorgesehen wird (organisatorische Steuerung). OPS.3.2.A18 deckt Regelungen beim Einsatz von Sub-Dienstleistenden ab (Unterweisung, Informationssicherheits-Regelungen, Verpflichtung, schriftliche/vertragliche Pflicht zur Einhaltung). OPS.3.2.A3 bezieht sich auf die Weitergabe/vertragliche Durchsetzung der mit den Nutzenden geregelten Bestimmungen an Sub-Dienstleistende (vertragliche Steuerung der Anforderungen). OPS.2.3.A24 sowie OPS.3.2.A19 fokussieren die Sicherheits-/Eignungs- bzw. Vertrauenswürdigkeitsüberprüfung des eingesetzten Personals bzw. Outsourcing-Personals durch geeignete Nachweise/Kriterien und schaffen damit eine Grundlage zur Vermeidung ungeprüfter bzw. unzureichend vertrauenswürdiger Dritter. Damit sind zentrale Kontroll- und Prüfmechanismen sowie vertragliche Einbindung von Sub-Dienstleistenden abgedeckt, aber nicht explizit die konkrete Autorisierung/Vorab-Zustimmung „durch den Auftraggeber“ als Zustimmungspflicht für die Unterauftragsvergabe.", "gap_notes": "Nicht vollständig abgedeckt: Die GS++-Kernforderung einer ausdrücklichen Autorisierung bzw. vorherigen Zustimmung des Auftraggebers zur Beauftragung/Einbindung von Unterauftragnehmern (Zustimmung als Freigabemechanismus für die Unterauftragnehmer-„Auswahl“ selbst) fehlt in den Kandidaten. Ebenfalls nicht explizit: Verhindern, dass der Hauptauftragnehmer eigenmächtig Subunternehmen einsetzt (Regel zu Unterbeauftragung ohne Zustimmung) sowie die konkrete Zuordnung, wer (Auftraggeber) Zugriff auf vertrauliche Informationen/kritische Prozesse erhält (‚Need-to-know‘-Zugriff als Folge der Zustimmung) wird nicht direkt adressiert."}