{"gs_ids": ["ORP.4.A24", "ORP.4.A6", "ORP.4.A2", "IND.1.A14"], "coverage": "teilweise", "confidence": 0.72, "rationale": "Die GS++-Anforderung BER.3.14 „Zugang nur durch zwei Personen“ (Absicherung nach Vier-Augen-Prinzip durch Aufteilung von Authentisierungsmitteln auf zwei Personen/Faktoren) wird am klarsten durch ORP.4.A24 „Vier-Augen-Prinzip für administrative Tätigkeiten“ abgedeckt: Dort werden bei Mehr-Faktor-Authentisierung die Faktoren auf zwei Personen verteilt und bei Passwörtern die Passwörter in zwei Teile zerlegt, die jeweils von einer der beiden Personen gehalten werden. Ergänzend stützen ORP.4.A6 „Vergabe von Zugangsberechtigungen“ und ORP.4.A2 „Einrichtung, Änderung und Entzug von Berechtigungen“ den organisatorischen Rahmen für das Vergeben/Entziehen bzw. das Betreiben von Zugriffen über definierte Berechtigungen (Dokumentation, Rollen/Bedarf), was für die praktische Umsetzung eines Zwei-Personen-Zugriffs relevant ist. IND.1.A14 „Starke Authentisierung an OT-Komponenten“ passt inhaltlich zur Zwei-Faktor/mehrfaktoriellen Absicherung privilegierter Konten (Wissen/Besitz/Biometrie), deckt aber nicht explizit „nur durch zwei Personen“ bzw. die konkrete Aufteilung auf zwei Personen im Sinne des Vier-Augen-Prinzips ab.", "gap_notes": "Nicht vollständig abgedeckt: BER.3.14 fordert explizit den Zugang nur durch zwei Personen (Vier-Augen-Prinzip) als Zugangsbeschränkung für Zugänge/Authentisierungsmittel. ORP.4.A24 trifft dies zwar für administrative Tätigkeiten, die übrigen gemappten Bausteine sind dagegen eher allgemeine Steuerung von Berechtigungen bzw. Starke/Mehrfaktor-Authentisierung ohne zwingende, explizite „zwei Personen“-Durchführung für den gesamten Zugangskontext."}