{"gs_ids": ["SYS.3.2.1.A18"], "coverage": "teilweise", "confidence": 0.78, "rationale": "Die GS-Anforderung SYS.3.2.1.A18 adressiert die Sensibilisierung der Nutzenden für die Fälschbarkeit biometrischer Merkmale (sinngemäß: „Benutzenden SOLLTEN für die Fälschbarkeit von biometrischen Merkmalen sensibilisiert werden“). Damit wird der Kernaspekt der GS++-Anforderung SENS.4.1.5 (Warnen vor Fälschbarkeit biometrischer Authentifizierungsmerkmale) inhaltlich getroffen. SYS.3.2.1.A18 enthält jedoch nicht explizit das konkrete Beispiel aus der GS++-Anforderung („Fingerabdruck von einer glatten Oberfläche abnehmen, um ein Gerät missbräuchlich zu entsperren“), sondern bleibt allgemeiner.", "gap_notes": "Nicht vollständig abgedeckt: das konkrete Angriffs-/Anwendungsbeispiel (Abnehmen eines Fingerabdrucks von einer glatten Oberfläche und missbräuchliches Entsperren). Außerdem geht GS++ zusätzlich auf genau diese Angriffsmotivation/Umsetzbarkeit durch das Beispiel ein; SYS.3.2.1.A18 formuliert die Sensibilisierung allgemeiner ohne dieses Szenario."}