{"gs_ids": ["DER.3.1.A5", "DER.3.2.A2", "DER.3.2.A14"], "coverage": "teilweise", "confidence": 0.56, "rationale": "Die GS++-Anforderung PERF.5.1.7 verlangt, dass der Status des Realisierungsplans (Fortschreibung von Umsetzungsdefiziten und dazugehörigen Risiken) fortlaufend überprüft und in einem Managementbericht dokumentiert wird, wobei die Ergebnisse auf Auditberichten sowie einer geforderten Eignungsprüfung basieren. \n- DER.3.1.A5 adressiert die Rückführung von Audit- und Revisions-Ergebnissen in den ISMS-Prozess sowie die Aufnahme der Ergebnisse in den regelmäßigen Bericht an die Institutionsleitung, inkl. festgehaltener Beseitigung von Mängeln.\n- DER.3.2.A2 ergänzt die laufende Korrektur- und Nachverfolgung von Abweichungen aus IS-Revisionen und das Fortschreiben des Umsetzungsstatus inkl. Statusdokumentation.\n- DER.3.2.A14 deckt die (risikoorientierte) Auswahl geprüfter Anforderungen/Objekte anhand vorheriger Ergebnisse und berücksichtigt bemängelte Anforderungen aus vorherigen IS-Revisionen, was als Grundlage für fortlaufende Status-/Defizitbetrachtung dienen kann.\nZusammen decken diese Kandidaten die Teile „kontinuierliche Nachverfolgung/Statusfortschreibung“ und „Berichterstattung an die Leitung“ sowie die Verbindung zu Prüf-/Audit-Ergebnissen ab. Die explizite Überführung in einen Managementbericht speziell als „Status des Realisierungsplans“ mit Dokumentation der damit verbundenen Risiken und die geforderte Eignungsprüfung sind jedoch nicht vollständig durch diese GS abgedeckt.", "gap_notes": "Nicht vollständig abgedeckt:\n- Spezifische Pflicht, die Ergebnisse ausdrücklich als „Status des Realisierungsplans“ zu dokumentieren (Managementbericht über Reduzierung bestehender Umsetzungsdefizite) ist nur indirekt abgedeckt.\n- Der GS++-Bezug auf die Dokumentation der zugehörigen Risiken (Risiko-Status im Realisierungsplan) ist in den gemappten Kandidaten nicht klar enthalten.\n- „Eignungsprüfung“ als eigene, explizite Prüfungskomponente zur Ableitung/Wirksamkeitsbewertung im Kontext dieser Realisierungsplan-Statusermittlung wird nicht eindeutig adressiert.\n- „Fortlaufende Überprüfung“ des Planstatus im Sinne eines definierten Monitoring-/Evaluierungszyklus über alle Maßnahmen hinweg ist nicht so konkret formuliert wie in PERF.5.1.7."}